{
  "content": "LOI 55 - Attaque hors tour du déclarant ................................................................................................ 68\nA. Attaque du déclarant acceptée ................................................................................................................................ 68\nB. Le déclarant doit reprendre son attaque .................................................................................................................. 68\nC. Le déclarant aurait pu obtenir une information ....................................................................................................... 68",
  "title": "LOI 55 - Attaque hors tour du déclarant ................................................................................................ 68",
  "references": [
    "55"
  ],
  "source_file": "Code2017-1.pdf",
  "referenced_by": [
    "55"
  ]
}