{
  "content": "LOI 57 - Attaque et jeu prématurés par un joueur de la défense ............................................................. 69\nA. Attaque prématurée pour la levée suivante ou jeu prématuré................................................................................ 69\nB. Le partenaire du joueur fautif ne peut se conformer à la rectification .................................................................... 69\nC. Le déclarant ou le mort a joué ................................................................................................................................. 69\nD. Jeu prématuré au tour de jouer de l’Adv. D .............................................................................................................. 69",
  "title": "LOI 57 - Attaque et jeu prématurés par un joueur de la défense ............................................................. 69",
  "references": [
    "57"
  ],
  "source_file": "Code2017-1.pdf",
  "referenced_by": [
    "57"
  ]
}